<?xml version="1.0" encoding="UTF-8" standalone="yes"?>
<items>
  
<item>
<title>NL | Utopia 1</title>
<thumbnail>https://i.imgur.com/XNDDjtX.jpg</thumbnail>
<link>ignore</link>
<fanart>https://i.imgur.com/6kJ57rR.jpg</fanart>  
<externallink>https://raw.githubusercontent.com/boomski/homeofcycling/master/STRM/hidiho_twitch1</externallink>
</item>  
  
<item>
<title>NL | Utopia 2</title>
<thumbnail>https://i.imgur.com/XNDDjtX.jpg</thumbnail>
<link>ignore</link>
<fanart>https://i.imgur.com/6kJ57rR.jpg</fanart>  
<externallink>https://raw.githubusercontent.com/boomski/homeofcycling/master/STRM/hidiho_twitch2</externallink>
</item> 
  
<item>
<title>NL | AFM TV</title>
<thumbnail>https://i.imgur.com/Yf0gTql.jpg</thumbnail>
<link>ignore</link>
<fanart>https://i.imgur.com/6kJ57rR.jpg</fanart>  
<externallink>https://raw.githubusercontent.com/boomski/homeofcycling/master/STRM/afmtv</externallink>
</item>  
  
</items>
